[
    {
        "Program name": "Bachelor of Science in Accounting",
        "Program Page url": "https://catalog.stonybrook.edu/content.php?catoid=8&navoid=483"
    },
    {
        "Program name": "Bachelor of Arts in Africana Studies",
        "Program Page url": "https://catalog.stonybrook.edu/content.php?catoid=8&navoid=483"
    },
    {
        "Program name": "Bachelor of Arts in Anthropology",
        "Program Page url": "https://www.stonybrook.edu/commcms/anthropology/undergraduate/"
    },
    {
        "Program name": "Bachelor of Science in Applied Mathematics & Statistics",
        "Program Page url": "https://catalog.stonybrook.edu/content.php?catoid=8&navoid=483"
    },
    {
        "Program name": "Bachelor of Arts in Art History & Criticism",
        "Program Page url": "https://catalog.stonybrook.edu/content.php?catoid=8&navoid=483"
    },
    {
        "Program name": "Bachelor of Arts in Art, Studio",
        "Program Page url": "https://www.stonybrook.edu/commcms/admitted/pdfs/ars.pdf"
    },
    {
        "Program name": "Bachelor of Arts in Asian & Asian American Studies",
        "Program Page url": "https://catalog.stonybrook.edu/content.php?catoid=8&navoid=483"
    },
    {
        "Program name": "Bachelor of Science in Astronomy/Planetary Sciences",
        "Program Page url": "https://catalog.stonybrook.edu/preview_program.php?catoid=8&poid=530"
    },
    {
        "Program name": "Bachelor of Science in Atmospheric and Oceanic Sciences",
        "Program Page url": "https://www.stonybrook.edu/commcms/somas/education/undergraduate/degrees/atm"
    },
    {
        "Program name": "Bachelor of Science in Biochemistry",
        "Program Page url": "https://catalog.stonybrook.edu/content.php?catoid=8&navoid=483"
    },
    {
        "Program name": "Bachelor of Arts in Biology",
        "Program Page url": "https://catalog.stonybrook.edu/content.php?catoid=8&navoid=483"
    },
    {
        "Program name": "Bachelor of Science in Biology",
        "Program Page url": "https://catalog.stonybrook.edu/content.php?catoid=8&navoid=483"
    },
    {
        "Program name": "Bachelor of Engineering in Biomedical Engineering",
        "Program Page url": "https://catalog.stonybrook.edu/content.php?catoid=8&navoid=483"
    },
    {
        "Program name": "Bachelor of Science in Business Management",
        "Program Page url": "https://catalog.stonybrook.edu/content.php?catoid=8&navoid=483"
    },
    {
        "Program name": "Bachelor of Engineering in Chemical & Molecular Engineering",
        "Program Page url": "https://www.stonybrook.edu/commcms/matscieng/undergraduate-cme/Specializations.php"
    },
    {
        "Program name": "Bachelor of Arts in Chemistry",
        "Program Page url": "https://catalog.stonybrook.edu/content.php?catoid=8&navoid=483"
    },
    {
        "Program name": "Bachelor of Science in Chemistry",
        "Program Page url": "https://catalog.stonybrook.edu/content.php?catoid=8&navoid=483"
    },
    {
        "Program name": "Bachelor of Engineering in Civil Engineering",
        "Program Page url": "https://catalog.stonybrook.edu/content.php?catoid=8&navoid=483"
    },
    {
        "Program name": "Bachelor of Science in Climate Science",
        "Program Page url": "https://catalog.stonybrook.edu/content.php?catoid=8&navoid=483"
    },
    {
        "Program name": "Bachelor of Science in Clinical Laboratory Sciences",
        "Program Page url": "https://healthprofessions.stonybrookmedicine.edu/programs/clinical"
    },
    {
        "Program name": "Bachelor of Science in Coastal Environmental Studies",
        "Program Page url": "https://www.youtube.com/watch?v=QXxdVuYRPrg"
    },
    {
        "Program name": "Bachelor of Arts in Communication",
        "Program Page url": "https://catalog.stonybrook.edu/content.php?catoid=8&navoid=483"
    },
    {
        "Program name": "Bachelor of Engineering in Computer Engineering",
        "Program Page url": "https://www.stonybrook.edu/commcms/electrical/undergraduate/index.php"
    },
    {
        "Program name": "Bachelor of Science in Computer Science",
        "Program Page url": "https://catalog.stonybrook.edu/content.php?catoid=8&navoid=483"
    },
    {
        "Program name": "Bachelor of Fine Arts in Creative Writing",
        "Program Page url": "https://catalog.stonybrook.edu/content.php?catoid=8&navoid=483"
    },
    {
        "Program name": "Bachelor of Science in Data Science",
        "Program Page url": "https://datasciencemajor.stanford.edu/academics/undergraduate-data-science-bs-program"
    },
    {
        "Program name": "Bachelor of Arts in Earth & Space Sciences",
        "Program Page url": "https://www.stonybrook.edu/commcms/geosciences/undergraduate/ba-ess"
    },
    {
        "Program name": "Minor in Accounting",
        "Program Page url": "https://catalog.stonybrook.edu/content.php?catoid=8&navoid=483"
    },
    {
        "Program name": "Minor in Africana Studies",
        "Program Page url": "https://catalog.stonybrook.edu/content.php?catoid=8&navoid=483"
    },
    {
        "Program name": "Minor in Anthropology",
        "Program Page url": "https://catalog.stonybrook.edu/content.php?catoid=8&navoid=483"
    },
    {
        "Program name": "Minor in Applied Mathematics and Statistics",
        "Program Page url": "https://catalog.stonybrook.edu/preview_program.php?catoid=8&poid=519&returnto=485&print"
    },
    {
        "Program name": "Minor in Art History",
        "Program Page url": "https://catalog.stonybrook.edu/content.php?catoid=8&navoid=483"
    },
    {
        "Program name": "Minor in Art, Studio",
        "Program Page url": "https://www.stonybrook.edu/ugrdbulletin/academicprograms/ars/"
    },
    {
        "Program name": "Minor in Asian American Studies",
        "Program Page url": "https://catalog.stonybrook.edu/content.php?catoid=8&navoid=485"
    },
    {
        "Program name": "Minor in Asian and Asian American Studies",
        "Program Page url": "https://www.stonybrook.edu/ugrdbulletin/academicprograms/aas/"
    },
    {
        "Program name": "Minor in Asian Thought",
        "Program Page url": "https://catalog.stonybrook.edu/content.php?catoid=8&navoid=483"
    },
    {
        "Program name": "Minor in Astronomy",
        "Program Page url": "https://catalog.stonybrook.edu/preview_program.php?catoid=8&poid=531&returnto=485"
    },
    {
        "Program name": "Minor in Bioengineering",
        "Program Page url": "https://catalog.stonybrook.edu/preview_program.php?catoid=8&poid=540&returnto=485"
    },
    {
        "Program name": "Minor in Biology",
        "Program Page url": "https://catalog.stonybrook.edu/content.php?catoid=8&navoid=483"
    },
    {
        "Program name": "Minor in Black Heritage Studies",
        "Program Page url": "https://www.stonybrook.edu/sb/bulletin/current-fall24/academicprograms/blh/degreesandrequirements.php"
    },
    {
        "Program name": "Minor in Chemistry",
        "Program Page url": "https://www.stonybrook.edu/commcms/chemistry/Education/undergraduate-program/undergradchemminor"
    },
    {
        "Program name": "Minor in China Studies",
        "Program Page url": "https://catalog.stonybrook.edu/content.php?catoid=8&navoid=483"
    },
    {
        "Program name": "Minor in Classics",
        "Program Page url": "https://catalog.stonybrook.edu/preview_program.php?catoid=8&poid=565&returnto=485"
    },
    {
        "Program name": "Minor in Climate Solutions",
        "Program Page url": "https://catalog.stonybrook.edu/content.php?catoid=8&navoid=483"
    },
    {
        "Program name": "Minor in Coastal Environmental Studies",
        "Program Page url": "https://catalog.stonybrook.edu/preview_program.php?catoid=8&poid=569&returnto=485"
    },
    {
        "Program name": "Minor in Communication",
        "Program Page url": "https://www.stonybrook.edu/commcms/journalism/undergraduate-students/minors.php"
    },
    {
        "Program name": "Minor in Communication and Innovation",
        "Program Page url": "https://catalog.stonybrook.edu/preview_program.php?catoid=8&poid=573&print"
    },
    {
        "Program name": "Minor in Computer Science",
        "Program Page url": "https://catalog.stonybrook.edu/content.php?catoid=8&navoid=483"
    },
    {
        "Program name": "Minor in Creative Writing",
        "Program Page url": "https://catalog.stonybrook.edu/content.php?catoid=8&navoid=483"
    },
    {
        "Program name": "Minor in Digital Arts",
        "Program Page url": "https://www.stonybrook.edu/sb/bulletin/current-fall24/academicprograms/dia/degreesandrequirements.php"
    },
    {
        "Program name": "Minor in Ecosystems and Human Impact",
        "Program Page url": "https://catalog.stonybrook.edu/content.php?catoid=8&navoid=483"
    },
    {
        "Program name": "Minor in Electrical Engineering",
        "Program Page url": "https://www.stonybrook.edu/ugrdbulletin/academicprograms/ese/"
    },
    {
        "Program name": "Minor in English",
        "Program Page url": "https://catalog.stonybrook.edu/content.php?catoid=8&navoid=483"
    },
    {
        "Program name": "Minor in Environmental Design, Policy, and Planning",
        "Program Page url": "https://www.stonybrook.edu/ugrdbulletin/academicprograms/edp/"
    },
    {
        "Program name": "Minor in Environmental Engineering",
        "Program Page url": "https://catalog.stonybrook.edu/content.php?catoid=8&navoid=483"
    },
    {
        "Program name": "Minor in Environmental Humanities",
        "Program Page url": "https://catalog.stonybrook.edu/preview_program.php?catoid=8&poid=615"
    },
    {
        "Program name": "Minor in Environmental Studies",
        "Program Page url": "https://catalog.stonybrook.edu/content.php?catoid=8&navoid=483"
    },
    {
        "Program name": "Minor in Ethnomusicology",
        "Program Page url": "https://www.stonybrook.edu/sb/bulletin/current-fall24/academicprograms/eth/index.pdf"
    },
    {
        "Program name": "Minor in Film and Screen Studies",
        "Program Page url": "https://catalog.stonybrook.edu/content.php?catoid=8&navoid=483"
    },
    {
        "Program name": "Minor in Filmmaking",
        "Program Page url": "https://catalog.stonybrook.edu/content.php?catoid=8&navoid=483"
    },
    {
        "Program name": "Minor in Finance",
        "Program Page url": "https://catalog.stonybrook.edu/content.php?catoid=8&navoid=483"
    },
    {
        "Program name": "Minor in French",
        "Program Page url": "https://www.stonybrook.edu/commcms/languages-cultural-studies/programs/French_Language_and_Literature.php"
    },
    {
        "Program name": "Minor in Geology",
        "Program Page url": "https://www.stonybrook.edu/commcms/geosciences/undergraduate/index.php"
    },
    {
        "Program name": "Minor in Geospatial Science",
        "Program Page url": "https://catalog.stonybrook.edu/content.php?catoid=8&navoid=483"
    },
    {
        "Program name": "Minor in Globalization Studies and International Relations",
        "Program Page url": "https://www.stonybrook.edu/ugrdbulletin/academicprograms/gli/"
    },
    {
        "Program name": "Minor in Health, Medicine, and Society",
        "Program Page url": "https://www.stonybrook.edu/commcms/sociology/undergraduate/"
    },
    {
        "Program name": "Minor in Hellenic Studies",
        "Program Page url": "https://catalog.stonybrook.edu/content.php?catoid=8&navoid=483"
    },
    {
        "Program name": "Minor in History",
        "Program Page url": "https://as.nyu.edu/departments/history/undergraduate/degree-options/the-minor-in-history.html"
    },
    {
        "Program name": "Minor in History of Health, Science, and the Environment",
        "Program Page url": "https://catalog.stonybrook.edu/content.php?catoid=8&navoid=483"
    },
    {
        "Program name": "Minor in Industrial Engineering",
        "Program Page url": "https://catalog.stonybrook.edu/content.php?catoid=8&navoid=483"
    },
    {
        "Program name": "Minor in Information Systems",
        "Program Page url": "https://catalog.stonybrook.edu/content.php?catoid=8&navoid=483"
    },
    {
        "Program name": "Minor in Italian American Studies",
        "Program Page url": "https://catalog.stonybrook.edu/content.php?catoid=8&navoid=483"
    },
    {
        "Program name": "Minor in Italian Studies",
        "Program Page url": "https://catalog.unc.edu/undergraduate/programs-study/italian-minor/italian-minor.pdf"
    },
    {
        "Program name": "Minor in Japanese Studies",
        "Program Page url": "https://www.stonybrook.edu/ugrdbulletin/academicprograms/jnh/"
    },
    {
        "Program name": "Minor in Jazz Music",
        "Program Page url": "https://www.stonybrook.edu/ugrdbulletin/academicprograms/jaz/"
    },
    {
        "Program name": "Minor in Journalism",
        "Program Page url": "https://catalog.stonybrook.edu/content.php?catoid=8&navoid=483"
    },
    {
        "Program name": "Minor in Judaic Studies",
        "Program Page url": "https://stonybrook.edu/academics/majors-minors-and-programs/"
    },
    {
        "Program name": "Minor in Korean Studies",
        "Program Page url": "https://www.stonybrook.edu/sb/bulletin/current-fall24/academicprograms/kor/degreesandrequirements.php"
    },
    {
        "Program name": "Minor in Latin American and Caribbean Studies",
        "Program Page url": "https://catalog.stonybrook.edu/content.php?catoid=8&navoid=483"
    },
    {
        "Program name": "Minor in Linguistics",
        "Program Page url": "https://linguistics.stonybrook.edu/academics/Undergraduate/requirement"
    },
    {
        "Program name": "Minor in Manufacturing Engineering",
        "Program Page url": "https://www.stonybrook.edu/commcms/matscieng/all_undergrad/undergrad/_esg/Minors.php"
    },
    {
        "Program name": "Minor in Marine Sciences",
        "Program Page url": "https://www.stonybrook.edu/commcms/somas/education/undergraduate/minors.php"
    },
    {
        "Program name": "Minor in Mass Communication",
        "Program Page url": "https://catalog.stonybrook.edu/content.php?catoid=8&navoid=483"
    },
    {
        "Program name": "Minor in Materials Science",
        "Program Page url": "https://catalog.stonybrook.edu/content.php?catoid=8&navoid=483"
    },
    {
        "Program name": "Minor in Mathematics",
        "Program Page url": "https://catalog.stonybrook.edu/content.php?catoid=8&navoid=483"
    },
    {
        "Program name": "Minor in Mechanical Engineering",
        "Program Page url": "https://catalog.stonybrook.edu/content.php?catoid=8&navoid=483"
    },
    {
        "Program name": "Minor in Middle Eastern Studies",
        "Program Page url": "https://catalog.stonybrook.edu/misc/catalog_list.php?catoid=8"
    },
    {
        "Program name": "Minor in Music",
        "Program Page url": "https://catalog.stonybrook.edu/content.php?catoid=8&navoid=483"
    },
    {
        "Program name": "Minor in Music and Technology",
        "Program Page url": "https://www.reddit.com/r/SBU/comments/1h7ikds/music_technology_minor/"
    },
    {
        "Program name": "Minor in Music Theory",
        "Program Page url": "https://catalog.stonybrook.edu/content.php?catoid=8&navoid=483"
    },
    {
        "Program name": "Minor in Nanotechnology Studies",
        "Program Page url": "https://www.stonybrook.edu/commcms/nanotech/_pdf/NTS-brochure.pdf"
    },
    {
        "Program name": "Minor in Native American and Indigenous Studies",
        "Program Page url": "https://www.stonybrook.edu/ugrdbulletin/academicprograms/nai/"
    },
    {
        "Program name": "Minor in Optics",
        "Program Page url": "https://catalog.stonybrook.edu/preview_program.php?catoid=8&poid=702&returnto=485&print"
    },
    {
        "Program name": "Minor in Philosophy",
        "Program Page url": "https://academic-guide.fsu.edu/minors"
    },
    {
        "Program name": "Minor in Physics",
        "Program Page url": "https://www.stonybrook.edu/ugrdbulletin/academicprograms/phy/"
    },
    {
        "Program name": "Minor in Political Science",
        "Program Page url": "https://catalog.stonybrook.edu/content.php?catoid=8&navoid=483"
    },
    {
        "Program name": "Minor in Professional Writing",
        "Program Page url": "https://catalog.stonybrook.edu/content.php?catoid=8&navoid=483"
    },
    {
        "Program name": "Minor in Real Estate and Insurance",
        "Program Page url": "https://catalog.stonybrook.edu/preview_program.php?catoid=8&poid=683&returnto=485"
    },
    {
        "Program name": "Minor in Religious Studies",
        "Program Page url": "https://catalog.stonybrook.edu/content.php?catoid=8&navoid=483"
    },
    {
        "Program name": "Minor in Russian Studies",
        "Program Page url": "https://catalog.stonybrook.edu/content.php?catoid=8&navoid=483"
    },
    {
        "Program name": "Minor in South Asian Studies",
        "Program Page url": "https://catalog.stonybrook.edu/content.php?catoid=8&navoid=483"
    },
    {
        "Program name": "Minor in Spanish Language and Literature",
        "Program Page url": "https://www.stonybrook.edu/ugrdbulletin/academicprograms/spn/"
    },
    {
        "Program name": "Minor in Sustainability Studies",
        "Program Page url": "https://catalog.stonybrook.edu/content.php?catoid=8&navoid=483"
    },
    {
        "Program name": "Minor in Television Writing",
        "Program Page url": "https://www.stonybrook.edu/commcms/creative-writing-film-television/"
    },
    {
        "Program name": "Minor in Theatre Arts",
        "Program Page url": "https://catalog.stonybrook.edu/content.php?catoid=8&navoid=483"
    },
    {
        "Program name": "Minor in Women's and Gender Studies",
        "Program Page url": "https://www.stonybrook.edu/ugrdbulletin/academicprograms/wst/"
    },
    {
        "Program name": "Minor in Writing and Rhetoric",
        "Program Page url": "https://www.stonybrook.edu/commcms/writrhet/undergrad/minor.php"
    }
]