[
    {
        "Program name": "Accounting",
        "Program Page url": "https://degrees.midway.edu/undergrad-majors-landing-page.html"
    },
    {
        "Program name": "Agricultural Business and Management, General",
        "Program Page url": "https://www.tuitionrewards.com/colleges/513/midway-university"
    },
    {
        "Program name": "Biology",
        "Program Page url": "https://degrees.midway.edu/undergrad-majors-landing-page.html"
    },
    {
        "Program name": "Biology (Minor)",
        "Program Page url": "https://degrees.midway.edu/undergrad-majors-landing-page.html"
    },
    {
        "Program name": "Bourbon Studies (Minor)",
        "Program Page url": "https://degrees.midway.edu/undergrad-majors-landing-page.html"
    },
    {
        "Program name": "Business Administration",
        "Program Page url": "https://degrees.midway.edu/undergrad-majors-landing-page.html"
    },
    {
        "Program name": "Business Administration - Human Resource Management",
        "Program Page url": "https://degrees.midway.edu/undergrad-majors-landing-page.html"
    },
    {
        "Program name": "Business Administration - Leadership Concentration",
        "Program Page url": "https://www.midway.edu/academics/majors-and-programs/business-administration.html"
    },
    {
        "Program name": "Chemistry (Minor)",
        "Program Page url": "https://degrees.midway.edu/undergrad-majors-landing-page.html"
    },
    {
        "Program name": "Coaching and Sport Leadership",
        "Program Page url": "https://degrees.midway.edu/coaching-and_sports.html"
    },
    {
        "Program name": "Computer Science",
        "Program Page url": "https://www.midway.edu/academics/majors-and-programs/computer-science.html"
    },
    {
        "Program name": "Criminal Justice",
        "Program Page url": "https://degrees.midway.edu/undergrad-majors-landing-page.html"
    },
    {
        "Program name": "Data Analytics",
        "Program Page url": "https://degrees.midway.edu/undergrad-majors-landing-page.html"
    },
    {
        "Program name": "Education (Elementary)",
        "Program Page url": "https://www.midway.edu/academics/majors-and-programs/elementary-education.html"
    },
    {
        "Program name": "Education (Middle School)",
        "Program Page url": "https://degrees.midway.edu/undergrad-majors-landing-page.html"
    },
    {
        "Program name": "Middle School Education - English (Area of Emphasis)",
        "Program Page url": "https://www.midway.edu/academics/majors-and-programs/middle-school-education.html"
    },
    {
        "Program name": "Middle School Education - Math (Area of Emphasis)",
        "Program Page url": "https://degrees.midway.edu/undergrad-majors-landing-page.html"
    },
    {
        "Program name": "Middle School Education - Science (Area of Emphasis)",
        "Program Page url": "https://degrees.midway.edu/undergrad-majors-landing-page.html"
    },
    {
        "Program name": "Middle School Education - Social Studies (Area of Emphasis)",
        "Program Page url": "https://www.midway.edu/academics/majors-and-programs/middle-school-education.html"
    },
    {
        "Program name": "Education (Secondary)",
        "Program Page url": "https://degrees.midway.edu/undergrad-majors-landing-page.html"
    },
    {
        "Program name": "Secondary Biology Education",
        "Program Page url": "https://www.midway.edu/academics/majors-and-programs/secondary-education.html"
    },
    {
        "Program name": "Secondary English Education",
        "Program Page url": "https://degrees.midway.edu/undergrad-majors-landing-page.html"
    },
    {
        "Program name": "Secondary Mathematics Education",
        "Program Page url": "https://degrees.midway.edu/undergrad-majors-landing-page.html"
    },
    {
        "Program name": "Education Studies",
        "Program Page url": "https://www.quora.com/What-is-the-difference-between-academics-and-education"
    },
    {
        "Program name": "Education Studies - English (Concentration)",
        "Program Page url": "https://degrees.midway.edu/undergrad-majors-landing-page.html"
    },
    {
        "Program name": "Education Studies - Math (Concentration)",
        "Program Page url": "https://degrees.midway.edu/undergrad-majors-landing-page.html"
    },
    {
        "Program name": "Education Studies - Science (Concentration)",
        "Program Page url": "https://degrees.midway.edu/undergrad-majors-landing-page.html"
    },
    {
        "Program name": "Education Studies - Social Studies (Concentration)",
        "Program Page url": "https://degrees.midway.edu/undergrad-majors-landing-page.html"
    },
    {
        "Program name": "Emergency Management/Homeland Security",
        "Program Page url": "https://www.pennfoster.edu/programs/legal/criminal-justice-bachelors-degree"
    },
    {
        "Program name": "English",
        "Program Page url": "https://degrees.midway.edu/undergrad-majors-landing-page.html"
    },
    {
        "Program name": "Environmental Science",
        "Program Page url": "https://degrees.midway.edu/undergrad-majors-landing-page.html"
    },
    {
        "Program name": "Equine Business and Sales",
        "Program Page url": "https://degrees.midway.edu/undergrad-majors-landing-page.html"
    },
    {
        "Program name": "Equine Studies",
        "Program Page url": "https://degrees.midway.edu/undergrad-majors-landing-page.html"
    },
    {
        "Program name": "Exercise Science",
        "Program Page url": "https://degrees.midway.edu/undergrad-majors-landing-page.html"
    },
    {
        "Program name": "Game Studies and Design",
        "Program Page url": "https://www.midway.edu/news/2024/game_design-press_release.html"
    },
    {
        "Program name": "Health Care Administration",
        "Program Page url": "https://degrees.midway.edu/undergrad-majors-landing-page.html"
    },
    {
        "Program name": "Health Service Preparatory Studies",
        "Program Page url": "https://www.midway.edu/academics/majors-and-programs/pre-professional-programs.html"
    },
    {
        "Program name": "Interdisciplinary Studies",
        "Program Page url": "https://degrees.midway.edu/undergrad-majors-landing-page.html"
    },
    {
        "Program name": "Liberal Arts and Humanities",
        "Program Page url": "https://www.midway.edu/academics/majors-and-programs/index.html"
    },
    {
        "Program name": "Marketing Communications",
        "Program Page url": "https://degrees.midway.edu/undergrad-majors-landing-page.html"
    },
    {
        "Program name": "Marketing Communications - Graphic Design (Specialization)",
        "Program Page url": "https://degrees.midway.edu/undergrad-majors-landing-page.html"
    },
    {
        "Program name": "Marketing Communications - Writing (Specialization)",
        "Program Page url": "https://degrees.midway.edu/undergrad-majors-landing-page.html"
    },
    {
        "Program name": "Mathematics",
        "Program Page url": "https://www.midway.edu/campaigns/stem.html"
    },
    {
        "Program name": "Music (Minor)",
        "Program Page url": "https://www.midway.edu/academics/majors-and-programs/music.html"
    },
    {
        "Program name": "Music (Minor) - General Music (Track)",
        "Program Page url": "https://degrees.midway.edu/undergrad-majors-landing-page.html"
    },
    {
        "Program name": "Music (Minor) - Music Education (Track)",
        "Program Page url": "https://www.midway.edu/academics/majors-and-programs/index.html"
    },
    {
        "Program name": "Music (Minor) - Music Therapy (Track)",
        "Program Page url": "https://degrees.midway.edu/undergrad-majors-landing-page.html"
    },
    {
        "Program name": "Music (Minor) - Performance (Track)",
        "Program Page url": "https://degrees.midway.edu/undergrad-majors-landing-page.html"
    },
    {
        "Program name": "Nursing (ADN)",
        "Program Page url": "https://degrees.midway.edu/undergrad-majors-landing-page.html"
    },
    {
        "Program name": "Nursing (Prelicensure BSN)",
        "Program Page url": "https://degrees.midway.edu/undergrad-majors-landing-page.html"
    },
    {
        "Program name": "Nursing (RN-BSN)",
        "Program Page url": "https://www.midway.edu/academics/majors-and-programs/rn-bsn.html"
    },
    {
        "Program name": "Nursing Administration",
        "Program Page url": "https://degrees.midway.edu/undergrad-majors-landing-page.html"
    },
    {
        "Program name": "Nursing Education",
        "Program Page url": "https://www.midway.edu/academics/majors-and-programs/msn.html"
    },
    {
        "Program name": "Physical Education Teaching and Coaching",
        "Program Page url": "https://www.midway.edu/academics/majors-and-programs/coaching-and-sport-leadership.html"
    },
    {
        "Program name": "Psychology",
        "Program Page url": "https://degrees.midway.edu/undergrad-majors-landing-page.html"
    },
    {
        "Program name": "Psychology - Alcohol and Drug Counseling (Concentration)",
        "Program Page url": "https://degrees.midway.edu/undergrad-majors-landing-page.html"
    },
    {
        "Program name": "Public Health",
        "Program Page url": "https://degrees.midway.edu/undergrad-majors-landing-page.html"
    },
    {
        "Program name": "Sport Management",
        "Program Page url": "https://degrees.midway.edu/undergrad-majors-landing-page.html"
    },
    {
        "Program name": "Sport Marketing",
        "Program Page url": "https://www.midway.edu/academics/majors-and-programs/sport-marketing.html"
    },
    {
        "Program name": "Sports Communication",
        "Program Page url": "https://degrees.midway.edu/undergrad-majors-landing-page.html"
    },
    {
        "Program name": "Supply Chain Management",
        "Program Page url": "https://degrees.midway.edu/undergrad-majors-landing-page.html"
    }
]