[
    {
        "QsWorldRanking": "1201-1400",
        "School": "Buchtel College of Arts and Sciences",
        "MaxFails": null,
        "MaxGPA": 4.0,
        "MinGPA": 3.0,
        "PreviousYearAcceptanceRates": null,
        "Term": "Fall",
        "LiveDate": null,
        "DeadlineDate": "February 15",
        "Fees": 11547,
        "AverageScholarshipAmount": null,
        "CostPerCredit": "$641.50 (Resident); $966.26 (Non-Resident)",
        "ScholarshipAmount": "Full-tuition scholarship and a stipend",
        "ScholarshipPercentage": null,
        "ScholarshipType": "Graduate Assistantships",
        "Program duration": null,
        "Tuition fee": "$11,547/Year (Resident); $17,392.68/Year (Non-Resident)",
        "Program name": "Master of Arts in Applied History and Public Humanities",
        "Program Page url": "https://www.uakron.edu/academics_majors/graduate_programs/"
    },
    {
        "QsWorldRanking": null,
        "School": "Buchtel College of Arts and Sciences",
        "MaxFails": null,
        "MaxGPA": 4.0,
        "MinGPA": 2.75,
        "PreviousYearAcceptanceRates": null,
        "Term": "Fall, Spring, Summer",
        "LiveDate": null,
        "DeadlineDate": null,
        "Fees": 9421.5,
        "AverageScholarshipAmount": null,
        "CostPerCredit": "628.10",
        "ScholarshipAmount": null,
        "ScholarshipPercentage": null,
        "ScholarshipType": null,
        "Program duration": "15 credit hours",
        "Tuition fee": "$9,421.50 for the 15-credit program (based on the Ohio Resident Distance Learning rate of $628.10 per credit hour)",
        "Program name": "Certificate in Applied Politics",
        "Program Page url": "https://www.uakron.edu/academics_majors/graduate_programs/"
    },
    {
        "QsWorldRanking": "1201-1400",
        "School": "School of Dance, Theatre, and Arts Administration",
        "MaxFails": null,
        "MaxGPA": 4.0,
        "MinGPA": 2.75,
        "PreviousYearAcceptanceRates": null,
        "Term": "Fall, Spring",
        "LiveDate": null,
        "DeadlineDate": null,
        "Fees": null,
        "AverageScholarshipAmount": null,
        "CostPerCredit": "$551.20 per credit hour (in-state); $857.00 per credit hour (out-of-state)",
        "ScholarshipAmount": "Full tuition waiver and a stipend of $10,000 for the academic year.",
        "ScholarshipPercentage": null,
        "ScholarshipType": "Graduate Assistantships",
        "Program duration": "2 years",
        "Tuition fee": null,
        "Program name": "Master of Arts in Arts Administration",
        "Program Page url": "https://www.uakron.edu/dtaa/artsadmin/"
    },
    {
        "QsWorldRanking": null,
        "School": "Buchtel College of Arts and Sciences",
        "MaxFails": null,
        "MaxGPA": 4,
        "MinGPA": 3,
        "PreviousYearAcceptanceRates": null,
        "Term": "Fall",
        "LiveDate": null,
        "DeadlineDate": "February 1",
        "Fees": null,
        "AverageScholarshipAmount": null,
        "CostPerCredit": "Ohio Resident: $570.10/credit, Non-Resident: $891.98/credit",
        "ScholarshipAmount": "$12,500 stipend (for 2023-2024)",
        "ScholarshipPercentage": "Full tuition waiver available via assistantship",
        "ScholarshipType": "Graduate Assistantships",
        "Program duration": null,
        "Tuition fee": null,
        "Program name": "Master of Arts in English: Composition",
        "Program Page url": "https://www.uakron.edu/academics_majors/graduate_programs/"
    },
    {
        "QsWorldRanking": null,
        "School": "Buchtel College of Arts and Sciences",
        "MaxFails": null,
        "MaxGPA": 4,
        "MinGPA": 3,
        "PreviousYearAcceptanceRates": null,
        "Term": "Fall",
        "LiveDate": null,
        "DeadlineDate": null,
        "Fees": 17684.16,
        "AverageScholarshipAmount": 12000,
        "CostPerCredit": "Ohio Resident: $552.63, Non-Resident: $854.23",
        "ScholarshipAmount": "$12,000 stipend plus a full tuition waiver",
        "ScholarshipPercentage": "100%",
        "ScholarshipType": "Graduate Assistantship",
        "Program duration": null,
        "Tuition fee": null,
        "Program name": "Master of Arts in English: Literature",
        "Program Page url": "https://english.osu.edu/"
    },
    {
        "QsWorldRanking": null,
        "School": "Buchtel College of Arts & Sciences",
        "MaxFails": null,
        "MaxGPA": 4,
        "MinGPA": 3,
        "PreviousYearAcceptanceRates": null,
        "Term": "Fall",
        "LiveDate": null,
        "DeadlineDate": null,
        "Fees": "$11,996.10/Year (Resident), $20,296.26/Year (Non-Resident)",
        "AverageScholarshipAmount": "$18,000 stipend plus full tuition waiver",
        "CostPerCredit": "$666.45 (Resident), $1127.57 (Non-Resident)",
        "ScholarshipAmount": "Stipend of approximately $18,000 for the nine-month academic year and a full tuition scholarship.",
        "ScholarshipPercentage": "100% tuition waiver for students with assistantships",
        "ScholarshipType": "Teaching and research assistantships",
        "Program duration": "2 years",
        "Tuition fee": "$11,996.10/Year (Resident), $20,296.26/Year (Non-Resident)",
        "Program name": "Master of Science in Geology",
        "Program Page url": "https://bulletin.uakron.edu/graduate/colleges-programs/arts-sciences/geosciences/geology-ms/"
    },
    {
        "QsWorldRanking": "1201-1400",
        "School": "Buchtel College of Arts and Sciences",
        "MaxFails": null,
        "MaxGPA": 4.0,
        "MinGPA": 3.0,
        "PreviousYearAcceptanceRates": null,
        "Term": "Fall",
        "LiveDate": null,
        "DeadlineDate": "January 15",
        "Fees": null,
        "AverageScholarshipAmount": null,
        "CostPerCredit": "$632.30/credit (Ohio Resident), $962.48/credit (Non-Ohio Resident)",
        "ScholarshipAmount": "23000",
        "ScholarshipPercentage": "100%",
        "ScholarshipType": "Graduate Assistantships",
        "Program duration": "4 to 6 years",
        "Tuition fee": null,
        "Program name": "PhD in Integrated Bioscience",
        "Program Page url": "https://www.uakron.edu/academics_majors/graduate_programs/"
    },
    {
        "QsWorldRanking": "1001-1200",
        "School": "Buchtel College of Arts and Sciences",
        "MaxFails": null,
        "MaxGPA": 4.0,
        "MinGPA": 3.0,
        "PreviousYearAcceptanceRates": null,
        "Term": "Fall, Spring",
        "LiveDate": null,
        "DeadlineDate": null,
        "Fees": null,
        "AverageScholarshipAmount": null,
        "CostPerCredit": "Ohio Resident: $618.11, Non-Ohio Resident: $953.51",
        "ScholarshipAmount": null,
        "ScholarshipPercentage": null,
        "ScholarshipType": "Graduate Teaching Assistantships",
        "Program duration": "2 years",
        "Tuition fee": "Ohio Resident (Graduate): approx. $11,126 per year; Non-Ohio Resident (Graduate): approx. $17,163 per year. Based on 2023-24 rates for 9 credits per semester.",
        "Program name": "Master of Science in Mathematics: Applied Mathematics",
        "Program Page url": "https://science.indianapolis.iu.edu/academics/degrees-and-programs/_degrees/mathematics-ms-iupui-mathms.html"
    },
    {
        "QsWorldRanking": null,
        "School": "Buchtel College of Arts and Sciences",
        "MaxFails": null,
        "MaxGPA": 4,
        "MinGPA": 3,
        "PreviousYearAcceptanceRates": null,
        "Term": "Fall, Spring",
        "LiveDate": null,
        "DeadlineDate": null,
        "Fees": "Ohio Resident: $8,480.10/Year; Non-Ohio Resident: $12,917.40/Year",
        "AverageScholarshipAmount": null,
        "CostPerCredit": "Ohio Resident: $565.34/credit; Non-Ohio Resident: $861.16/credit",
        "ScholarshipAmount": "Graduate assistantships provide a full tuition waiver and a minimum stipend of $12,000 for a 9-month appointment.",
        "ScholarshipPercentage": null,
        "ScholarshipType": "Graduate Assistantships",
        "Program duration": "2 years",
        "Tuition fee": "Ohio Resident: $8,480.10/Year; Non-Ohio Resident: $12,917.40/Year",
        "Program name": "Master of Arts in Political Science: Applied Politics",
        "Program Page url": "https://www.uakron.edu/academics_majors/graduate_programs/"
    },
    {
        "QsWorldRanking": "801-1000",
        "School": "School of Polymer Science and Polymer Engineering",
        "MaxFails": null,
        "MaxGPA": 4,
        "MinGPA": 3,
        "PreviousYearAcceptanceRates": null,
        "Term": "Fall, Spring, Summer",
        "LiveDate": null,
        "DeadlineDate": null,
        "Fees": "$18,383.40/Year",
        "AverageScholarshipAmount": null,
        "CostPerCredit": "$662.30/credit (Resident), $1,021.30/credit (Non-Resident)",
        "ScholarshipAmount": null,
        "ScholarshipPercentage": null,
        "ScholarshipType": "Fellowships, Research Assistantships, Teaching Assistantships",
        "Program duration": null,
        "Tuition fee": "$18,383.40/Year",
        "Program name": "Master of Science in Polymer Engineering",
        "Program Page url": "https://www.uakron.edu/polymer/programs/ms-polymer-engineering"
    },
    {
        "QsWorldRanking": null,
        "School": "School of Polymer Science and Polymer Engineering",
        "MaxFails": null,
        "MaxGPA": 4,
        "MinGPA": 3,
        "PreviousYearAcceptanceRates": null,
        "Term": "Fall",
        "LiveDate": null,
        "DeadlineDate": null,
        "Fees": null,
        "AverageScholarshipAmount": "$30,000 per year stipend",
        "CostPerCredit": "Ohio Resident: $565.34/credit hour; Non-Ohio Resident: $888.64/credit hour",
        "ScholarshipAmount": "$30,000 per year stipend plus tuition and fee waiver",
        "ScholarshipPercentage": "100% of full-time Ph.D. students receive a graduate assistantship",
        "ScholarshipType": "Graduate Assistantship",
        "Program duration": "4.5 years",
        "Tuition fee": null,
        "Program name": "PhD in Polymer Science",
        "Program Page url": "https://www.uakron.edu/polymer/programs/phd-polymer-science"
    },
    {
        "QsWorldRanking": null,
        "School": "Buchtel College of Arts and Sciences",
        "MaxFails": null,
        "MaxGPA": 4,
        "MinGPA": 3.0,
        "PreviousYearAcceptanceRates": null,
        "Term": "Fall",
        "LiveDate": null,
        "DeadlineDate": "December 1",
        "Fees": null,
        "AverageScholarshipAmount": "Stipend of $18,000 - $18,500 per year",
        "CostPerCredit": "Ohio Resident: $565.72/credit hour; Non-Ohio Resident: $886.50/credit hour",
        "ScholarshipAmount": "Full tuition waiver plus a stipend of $18,000 - $18,500 per year",
        "ScholarshipPercentage": "100% tuition coverage",
        "ScholarshipType": "Graduate Assistantships",
        "Program duration": "5 years",
        "Tuition fee": null,
        "Program name": "PhD in Psychology: Industrial/Organizational",
        "Program Page url": "https://www.uakron.edu/academics_majors/graduate_programs/"
    },
    {
        "QsWorldRanking": "1001-1200",
        "School": "Buchtel College of Arts and Sciences",
        "MaxFails": null,
        "MaxGPA": 4,
        "MinGPA": 3,
        "PreviousYearAcceptanceRates": null,
        "Term": "Fall",
        "LiveDate": null,
        "DeadlineDate": "December 1",
        "Fees": "$10,635.94/Year (Ohio Resident), $15,642.10/Year (Non-Ohio Resident)",
        "AverageScholarshipAmount": null,
        "CostPerCredit": "$514.88 (Ohio Resident), $793.00 (Non-Ohio Resident)",
        "ScholarshipAmount": "Full tuition waiver plus a minimum stipend of $10,000 for the nine-month academic year for graduate assistants.",
        "ScholarshipPercentage": "100% tuition waiver for graduate assistants.",
        "ScholarshipType": "Graduate Assistantships, Internships",
        "Program duration": "2 years",
        "Tuition fee": "$10,635.94/Year (Ohio Resident), $15,642.10/Year (Non-Ohio Resident)",
        "Program name": "Master of Arts in Psychology: Industrial/Organizational",
        "Program Page url": "https://psychology.rice.edu/graduate/miop"
    },
    {
        "QsWorldRanking": "1201-1400",
        "School": "School of Speech-Language Pathology and Audiology",
        "MaxFails": null,
        "MaxGPA": 4,
        "MinGPA": 3,
        "PreviousYearAcceptanceRates": null,
        "Term": "Fall",
        "LiveDate": null,
        "DeadlineDate": "January 15, 2026",
        "Fees": null,
        "AverageScholarshipAmount": null,
        "CostPerCredit": "$665.41 per credit hour for Ohio Residents, $1,059.95 per credit hour for Non-Ohio Residents",
        "ScholarshipAmount": null,
        "ScholarshipPercentage": null,
        "ScholarshipType": "Endowed scholarships",
        "Program duration": "5 semesters",
        "Tuition fee": "$665.41 per credit hour for Ohio Residents, $1,059.95 per credit hour for Non-Ohio Residents (2024-2025 rates). The program requires a minimum of 53 credits.",
        "Program name": "Master of Arts in Speech-Language Pathology",
        "Program Page url": "https://hesp.umd.edu/undergraduate/program-highlights-master-arts-program-speech-language-pathology-%28spla%29"
    },
    {
        "QsWorldRanking": "1201-1400",
        "School": "Buchtel College of Arts and Sciences",
        "MaxFails": null,
        "MaxGPA": 4,
        "MinGPA": 3,
        "PreviousYearAcceptanceRates": null,
        "Term": "Fall, Spring",
        "LiveDate": null,
        "DeadlineDate": null,
        "Fees": null,
        "AverageScholarshipAmount": null,
        "CostPerCredit": "$596.16 (In-state), $866.40 (Out-of-state)",
        "ScholarshipAmount": null,
        "ScholarshipPercentage": null,
        "ScholarshipType": "Assistantships, Fellowships, Scholarships",
        "Program duration": "2 years",
        "Tuition fee": null,
        "Program name": "Master of Science in Statistics",
        "Program Page url": "https://www.uakron.edu/academics_majors/graduate_programs/"
    },
    {
        "QsWorldRanking": "1201-1400",
        "School": "School of Speech-Language Pathology and Audiology",
        "MaxFails": null,
        "MaxGPA": 4,
        "MinGPA": 3,
        "PreviousYearAcceptanceRates": null,
        "Term": "Fall",
        "LiveDate": null,
        "DeadlineDate": "January 15",
        "Fees": "An estimated $27,713 per year for a full-time resident student, which includes per-credit tuition and mandatory program fees.",
        "AverageScholarshipAmount": null,
        "CostPerCredit": "$690.42 (Resident), $1,041.02 (Non-Resident). An additional $3,500 Career Advantage Au.D. Grad Program Fee is assessed per term.",
        "ScholarshipAmount": null,
        "ScholarshipPercentage": null,
        "ScholarshipType": "Graduate assistantships, tuition scholarships, and research grants",
        "Program duration": "4 years",
        "Tuition fee": "An estimated $27,713 per year for a full-time resident student, which includes per-credit tuition and mandatory program fees.",
        "Program name": "Doctor of Audiology (Au.D.)",
        "Program Page url": "https://www.uakron.edu/academics_majors/graduate_programs/"
    },
    {
        "QsWorldRanking": null,
        "School": "Buchtel College of Arts and Sciences",
        "MaxFails": null,
        "MaxGPA": 4.0,
        "MinGPA": 3.0,
        "PreviousYearAcceptanceRates": null,
        "Term": "Fall, Spring",
        "LiveDate": null,
        "DeadlineDate": null,
        "Fees": "$13,636/year (in-state), $21,488/year (out-of-state)",
        "AverageScholarshipAmount": null,
        "CostPerCredit": "$496.06 (in-state), $817.00 (out-of-state)",
        "ScholarshipAmount": null,
        "ScholarshipPercentage": null,
        "ScholarshipType": "Graduate Assistantships (Teaching and Research), Fellowships",
        "Program duration": "2 years",
        "Tuition fee": "$13,636/year (in-state), $21,488/year (out-of-state)",
        "Program name": "Master of Science in Biology",
        "Program Page url": "https://bulletin.uakron.edu/graduate/colleges-programs/arts-sciences/biology/biology-ms/"
    },
    {
        "QsWorldRanking": null,
        "School": "College of Business",
        "MaxFails": null,
        "MaxGPA": 4.0,
        "MinGPA": 3.0,
        "PreviousYearAcceptanceRates": null,
        "Term": "Fall, Spring, and Summer",
        "LiveDate": null,
        "DeadlineDate": null,
        "Fees": 20441.4,
        "AverageScholarshipAmount": null,
        "CostPerCredit": "$681.38 (in-state), $989.98 (out-of-state)",
        "ScholarshipAmount": "The University Fellowship provides a $12,000 stipend plus a full tuition scholarship.",
        "ScholarshipPercentage": null,
        "ScholarshipType": "Assistantships, Fellowships, Merit-based scholarships",
        "Program duration": "30 credit hours",
        "Tuition fee": 20441.4,
        "Program name": "Master of Science in Business: Accountancy",
        "Program Page url": "https://bulletin.uakron.edu/graduate/colleges-programs/business-administration/accountancy/accounting-msa/"
    },
    {
        "QsWorldRanking": "801-1000",
        "School": "George W. and Angelina S. College of Business Administration",
        "MaxFails": null,
        "MaxGPA": 4,
        "MinGPA": 2.75,
        "PreviousYearAcceptanceRates": null,
        "Term": "Fall, Spring, Summer",
        "LiveDate": null,
        "DeadlineDate": null,
        "Fees": null,
        "AverageScholarshipAmount": null,
        "CostPerCredit": "$665.48/credit (Ohio Resident), $1,075.60/credit (Non-Ohio Resident)",
        "ScholarshipAmount": null,
        "ScholarshipPercentage": null,
        "ScholarshipType": "Merit-based scholarships, Graduate Assistantships",
        "Program duration": "As little as one year",
        "Tuition fee": "$19,964.40 (Ohio Resident, total program), $32,268 (Non-Ohio Resident, total program)",
        "Program name": "Master of Science in Business: Management, Information Systems",
        "Program Page url": "https://www.uakron.edu/academics_majors/graduate_programs/"
    },
    {
        "QsWorldRanking": "1001-1200",
        "School": "College of Business",
        "MaxFails": null,
        "MaxGPA": 4.0,
        "MinGPA": 3.0,
        "PreviousYearAcceptanceRates": null,
        "Term": "Fall, Spring, Summer",
        "LiveDate": null,
        "DeadlineDate": null,
        "Fees": "$9,747/Year (Ohio Resident)",
        "AverageScholarshipAmount": null,
        "CostPerCredit": "Ohio Resident: $649.80, Non-Ohio Resident: $965.72",
        "ScholarshipAmount": "Up to $1,000",
        "ScholarshipPercentage": null,
        "ScholarshipType": "Fellowships, Assistantships, Merit-based scholarships",
        "Program duration": null,
        "Tuition fee": "$9,747/Year (Ohio Resident)",
        "Program name": "Master of Science in Business: Management, Supply Chain Management",
        "Program Page url": "https://www.uakron.edu/academics_majors/graduate_programs/"
    },
    {
        "QsWorldRanking": "801-1000",
        "School": "Buchtel College of Arts and Sciences",
        "MaxFails": null,
        "MaxGPA": 4.0,
        "MinGPA": 3.0,
        "PreviousYearAcceptanceRates": null,
        "Term": "Fall, Spring",
        "LiveDate": null,
        "DeadlineDate": null,
        "Fees": "In addition to tuition, there is a $12.00 per credit hour Chemistry Fee, a General Service Fee ($45.68/credit), and a Technology Fee ($15.50/credit).",
        "AverageScholarshipAmount": null,
        "CostPerCredit": "$505.74 (In-State); $812.24 (Out-of-State)",
        "ScholarshipAmount": null,
        "ScholarshipPercentage": null,
        "ScholarshipType": "University-wide scholarships",
        "Program duration": "2 years",
        "Tuition fee": "$10,420.56/Year (In-State, estimate based on 18 credits including all fees)",
        "Program name": "Master of Science in Chemistry",
        "Program Page url": "https://www.uakron.edu/academics_majors/graduate_programs/"
    },
    {
        "QsWorldRanking": null,
        "School": "Buchtel College of Arts and Sciences",
        "MaxFails": null,
        "MaxGPA": 4.0,
        "MinGPA": 3.0,
        "PreviousYearAcceptanceRates": null,
        "Term": "Fall, Spring",
        "LiveDate": null,
        "DeadlineDate": null,
        "Fees": null,
        "AverageScholarshipAmount": null,
        "CostPerCredit": "Ohio Resident: $577.84/credit, Non-Ohio Resident: $901.34/credit",
        "ScholarshipAmount": null,
        "ScholarshipPercentage": "100% tuition scholarship",
        "ScholarshipType": "Teaching and Research Assistantships",
        "Program duration": "Requires a minimum of 90 semester credits beyond the baccalaureate degree.",
        "Tuition fee": null,
        "Program name": "PhD in Chemistry",
        "Program Page url": "https://bulletin.auburn.edu/thegraduateschool/graduatedegreesoffered/chemistryandbiochemistrymsphd_major/chemistry_phd/"
    },
    {
        "QsWorldRanking": null,
        "School": "School of Education",
        "MaxFails": null,
        "MaxGPA": 4,
        "MinGPA": 3,
        "PreviousYearAcceptanceRates": null,
        "Term": "Fall, Spring, and Summer",
        "LiveDate": null,
        "DeadlineDate": null,
        "Fees": "$6,717.20/Semester",
        "AverageScholarshipAmount": null,
        "CostPerCredit": "Ohio Resident: $517.22/credit; Non-Ohio Resident: $834.41/credit",
        "ScholarshipAmount": "Stipends range between $8,000 and $18,000 for the nine-month academic year, plus a full tuition scholarship and waiver of the general university fee.",
        "ScholarshipPercentage": null,
        "ScholarshipType": "Graduate Assistantships",
        "Program duration": "36 credit hours",
        "Program name": "Master of Arts in Child and Family Development",
        "Program Page url": "https://www.uakron.edu/academics_majors/graduate_programs/"
    },
    {
        "QsWorldRanking": "1001-1200",
        "School": "Buchtel College of Arts and Sciences",
        "MaxFails": null,
        "MaxGPA": 4.0,
        "MinGPA": 3.0,
        "PreviousYearAcceptanceRates": null,
        "Term": "Fall, Spring, Summer",
        "LiveDate": null,
        "DeadlineDate": null,
        "Fees": null,
        "AverageScholarshipAmount": null,
        "CostPerCredit": "$526.02 for Ohio residents, $846.63 for non-residents",
        "ScholarshipAmount": null,
        "ScholarshipPercentage": null,
        "ScholarshipType": "Graduate Assistantships",
        "Program duration": "1.5 to 2 years",
        "Tuition fee": "$9,468.36/Year for Ohio residents, $15,239.34/Year for non-residents (based on 18 credits per year)",
        "Program name": "Master of Arts in Communication",
        "Program Page url": "https://www.uakron.edu/academics_majors/graduate_programs/"
    },
    {
        "QsWorldRanking": null,
        "School": "College of Health and Human Sciences",
        "MaxFails": null,
        "MaxGPA": 4.0,
        "MinGPA": 3.25,
        "PreviousYearAcceptanceRates": null,
        "Term": "Fall",
        "LiveDate": null,
        "DeadlineDate": "December 1, 2025",
        "Fees": "$18,894.30/Year (Ohio Resident)",
        "AverageScholarshipAmount": null,
        "CostPerCredit": "$629.81/credit hour (Ohio Resident)",
        "ScholarshipAmount": "$15,000 stipend and a full tuition waiver",
        "ScholarshipPercentage": null,
        "ScholarshipType": "Graduate assistantships",
        "Program duration": "five to six years",
        "Tuition fee": "$18,894.30/Year (Ohio Resident)",
        "Program name": "PhD in Counseling Psychology",
        "Program Page url": "https://www.uakron.edu/academics_majors/graduate_programs/"
    },
    {
        "QsWorldRanking": "1001-1200",
        "School": "School of Counseling",
        "MaxFails": 0,
        "MaxGPA": 4.0,
        "MinGPA": 2.75,
        "PreviousYearAcceptanceRates": null,
        "Term": "Fall",
        "LiveDate": null,
        "DeadlineDate": null,
        "Fees": "$14,604/Year (in-state)",
        "AverageScholarshipAmount": null,
        "CostPerCredit": "$608.44/credit (in-state)",
        "ScholarshipAmount": null,
        "ScholarshipPercentage": null,
        "ScholarshipType": "Assistantships, Fellowships, Scholarships",
        "Program duration": "2 years",
        "Tuition fee": "$14,604/Year (in-state)",
        "Program name": "Master of Arts in Counseling: Clinical Mental Health Counseling",
        "Program Page url": "https://www.uakron.edu/academics_majors/graduate_programs/"
    },
    {
        "QsWorldRanking": null,
        "School": "School of Counseling",
        "MaxFails": null,
        "MaxGPA": 4.0,
        "MinGPA": 2.75,
        "PreviousYearAcceptanceRates": null,
        "Term": "Fall",
        "LiveDate": "August 2025",
        "DeadlineDate": "January 15, 2026",
        "AverageScholarshipAmount": null,
        "CostPerCredit": "$571.98/credit (in-state), $883.29/credit (out-of-state)",
        "ScholarshipAmount": null,
        "ScholarshipPercentage": null,
        "ScholarshipType": "Scholarships, Assistantships, Fellowships",
        "Program duration": "2.5 years",
        "Tuition fee": "$13,728/Year (in-state), $21,199/Year (out-of-state)",
        "Program name": "Master of Arts in Counseling: Marriage and Family Therapy/Counseling",
        "Program Page url": "https://www.uakron.edu/academics_majors/graduate_programs/"
    },
    {
        "QsWorldRanking": null,
        "School": "LeBron James Family Foundation School of Education",
        "MaxFails": null,
        "MaxGPA": 4.0,
        "MinGPA": 2.75,
        "PreviousYearAcceptanceRates": null,
        "Term": "Summer, Fall",
        "LiveDate": "August of the year prior to admission",
        "DeadlineDate": "January 15",
        "Fees": "11554/Year",
        "AverageScholarshipAmount": null,
        "CostPerCredit": "566.23/Credit",
        "ScholarshipAmount": null,
        "ScholarshipPercentage": null,
        "ScholarshipType": "Assistantships, Fellowships, Scholarships",
        "Program duration": "2 years",
        "Tuition fee": "11554/Year",
        "Program name": "Master of Arts in Education: School Counseling",
        "Program Page url": "https://www.uakron.edu/academics_majors/graduate_programs/"
    },
    {
        "QsWorldRanking": null,
        "School": "College of Engineering and Polymer Science",
        "MaxFails": null,
        "MaxGPA": 4.0,
        "MinGPA": 3.0,
        "PreviousYearAcceptanceRates": null,
        "Term": "Fall, Spring",
        "LiveDate": null,
        "DeadlineDate": null,
        "Fees": "$15,162.12/Year (In-State), $22,151.52/Year (Out-of-State)",
        "AverageScholarshipAmount": null,
        "CostPerCredit": "$766.70/credit (In-State), $1,155.00/credit (Out-of-State)",
        "ScholarshipAmount": "Stipends for the 2023-24 academic year are $30,000",
        "ScholarshipPercentage": null,
        "ScholarshipType": "Teaching or research assistantships",
        "Program duration": null,
        "Tuition fee": "$15,162.12/Year (In-State), $22,151.52/Year (Out-of-State)",
        "Program name": "PhD in Engineering: Polymer Engineering",
        "Program Page url": "https://www.uakron.edu/academics_majors/graduate_programs/"
    },
    {
        "QsWorldRanking": null,
        "School": "College of Business",
        "MaxFails": null,
        "MaxGPA": 4.0,
        "MinGPA": 3.0,
        "PreviousYearAcceptanceRates": null,
        "Term": "Fall, Spring, Summer",
        "LiveDate": null,
        "DeadlineDate": null,
        "AverageScholarshipAmount": null,
        "CostPerCredit": 940.7,
        "ScholarshipAmount": null,
        "ScholarshipPercentage": null,
        "ScholarshipType": "Graduate assistantships",
        "Program duration": "Two years",
        "Tuition fee": "$16,932.60/Year (Ohio Resident)",
        "Program name": "Master of Business Administration with Concentration in Business Analytics",
        "Program Page url": "https://www.uakron.edu/academics_majors/graduate_programs/"
    },
    {
        "QsWorldRanking": null,
        "School": "College of Business",
        "MaxFails": null,
        "MaxGPA": 4.0,
        "MinGPA": 3.0,
        "PreviousYearAcceptanceRates": null,
        "Term": "Fall, Spring, and Summer",
        "LiveDate": null,
        "DeadlineDate": null,
        "Fees": null,
        "AverageScholarshipAmount": null,
        "CostPerCredit": "$776.42 per credit hour for Ohio residents, $1,192.83 per credit hour for non-residents",
        "ScholarshipAmount": null,
        "ScholarshipPercentage": null,
        "ScholarshipType": "Merit-based, Need-based",
        "Program duration": "As few as 12 months, or up to six years",
        "Tuition fee": "$27,951.12 (Total program tuition for Ohio residents)",
        "Program name": "Master of Business Administration with Concentration in Finance",
        "Program Page url": "https://www.uakron.edu/academics_majors/graduate_programs/"
    },
    {
        "QsWorldRanking": null,
        "School": "College of Business",
        "MaxFails": null,
        "MaxGPA": 4.0,
        "MinGPA": 3.0,
        "PreviousYearAcceptanceRates": null,
        "Term": "Fall, Spring, Summer",
        "LiveDate": null,
        "DeadlineDate": null,
        "Fees": null,
        "AverageScholarshipAmount": null,
        "CostPerCredit": "Ohio Resident: $686.04/credit; Non-Ohio Resident: $1,058.22/credit",
        "ScholarshipAmount": "Stipends for graduate assistantships range from $4,500 to $9,000 per academic year.",
        "ScholarshipPercentage": null,
        "ScholarshipType": "Merit-based scholarships, Graduate Assistantships",
        "Program duration": "36 credit hours",
        "Tuition fee": "Approximately $24,700 for the entire program for Ohio residents and $38,100 for non-residents.",
        "Program name": "Master of Business Administration with Concentration in Risk Management & Insurance",
        "Program Page url": "https://www.uakron.edu/academics_majors/graduate_programs/"
    },
    {
        "QsWorldRanking": null,
        "School": null,
        "MaxFails": null,
        "MaxGPA": null,
        "MinGPA": null,
        "PreviousYearAcceptanceRates": null,
        "Term": null,
        "LiveDate": null,
        "DeadlineDate": null,
        "Fees": null,
        "AverageScholarshipAmount": null,
        "CostPerCredit": null,
        "ScholarshipAmount": null,
        "ScholarshipPercentage": null,
        "ScholarshipType": null,
        "Program duration": null,
        "Tuition fee": null,
        "Program name": "Master of Business Administration with Concentration in Global Technological Innovation",
        "Program Page url": "https://www.wtamu.edu/academics/college-business/academics/graduate-programs/index.html"
    },
    {
        "QsWorldRanking": null,
        "School": "College of Business",
        "MaxFails": null,
        "MaxGPA": 4.0,
        "MinGPA": 2.75,
        "PreviousYearAcceptanceRates": null,
        "Term": "Fall, Spring, Summer",
        "LiveDate": null,
        "DeadlineDate": null,
        "Fees": null,
        "AverageScholarshipAmount": null,
        "CostPerCredit": "Ohio Resident: $690.62/credit; Non-Ohio Resident: $1,079.12/credit",
        "ScholarshipAmount": "Minimum stipend of $12,000 for a nine-month contract, plus a full tuition scholarship for graduate assistants.",
        "ScholarshipPercentage": "100% tuition waiver for graduate assistants",
        "ScholarshipType": "Graduate Assistantships",
        "Program duration": "As little as 18 months",
        "Tuition fee": "Ohio Resident: $28,670.40; Non-Ohio Resident: $42,656.40",
        "Program name": "Master of Business Administration with Concentration in Health Care Management",
        "Program Page url": "https://www.uakron.edu/academics_majors/graduate_programs/"
    },
    {
        "QsWorldRanking": null,
        "School": "College of Business Administration",
        "MaxFails": null,
        "MaxGPA": 4.0,
        "MinGPA": 2.75,
        "PreviousYearAcceptanceRates": null,
        "Term": "Fall, Spring, Summer",
        "LiveDate": null,
        "DeadlineDate": null,
        "Fees": null,
        "AverageScholarshipAmount": null,
        "CostPerCredit": "Ohio Resident: $711.53; Non-Ohio Resident: $1,175.38",
        "ScholarshipAmount": "$500 - $2,500",
        "ScholarshipPercentage": null,
        "ScholarshipType": "Merit-based, Need-based",
        "Program duration": "As little as one year (full-time) or at a student’s own pace (part-time)",
        "Tuition fee": "Ohio Resident: $25,615.08 (total for 36 credits); Non-Ohio Resident: $42,313.68 (total for 36 credits)",
        "Program name": "Master of Business Administration with Concentration in Interdisciplinary",
        "Program Page url": "https://bulletin.uakron.edu/graduate/colleges-programs/business-administration/business-interdisciplinary-mba/business-interdisciplinary-mba.pdf"
    },
    {
        "QsWorldRanking": null,
        "School": "College of Business",
        "MaxFails": null,
        "MaxGPA": 4.0,
        "MinGPA": 3.0,
        "PreviousYearAcceptanceRates": null,
        "Term": "Fall, Spring, Summer",
        "LiveDate": null,
        "DeadlineDate": null,
        "Fees": null,
        "AverageScholarshipAmount": null,
        "CostPerCredit": "$681.42 per credit hour (Ohio Resident), $1,073.34 per credit hour (Non-Ohio Resident)",
        "ScholarshipAmount": "$1,000 to $4,000",
        "ScholarshipPercentage": null,
        "ScholarshipType": "Merit-based, Assistantships",
        "Program duration": "1 to 6 years",
        "Tuition fee": "The total investment for the MBA program can be as low as $25,000",
        "Program name": "Master of Business Administration with Concentration in International Business",
        "Program Page url": "https://www.uakron.edu/academics_majors/graduate_programs/"
    },
    {
        "QsWorldRanking": null,
        "School": "College of Business",
        "MaxFails": 2,
        "MaxGPA": 4.0,
        "MinGPA": 2.75,
        "PreviousYearAcceptanceRates": null,
        "Term": "Fall, Spring, Summer",
        "LiveDate": null,
        "DeadlineDate": null,
        "Fees": "24837.12 (Ohio Resident), 35727.12 (Non-Ohio Resident)",
        "AverageScholarshipAmount": null,
        "CostPerCredit": "$689.92 (Ohio Resident), $992.42 (Non-Ohio Resident)",
        "ScholarshipAmount": "Up to $2,000; Graduate Assistantships include a full tuition waiver and stipend",
        "ScholarshipPercentage": null,
        "ScholarshipType": "Merit-based, Need-based, Fellowships, Graduate Assistantships",
        "Program duration": "1-5 years",
        "Tuition fee": "$24,837.12 (Ohio Resident, for 36 credits), $35,727.12 (Non-Ohio Resident, for 36 credits)",
        "Program name": "Master of Business Administration with Concentration in Management",
        "Program Page url": "https://www.uakron.edu/academics_majors/graduate_programs/"
    },
    {
        "QsWorldRanking": null,
        "School": "College of Business",
        "MaxFails": null,
        "MaxGPA": 4.0,
        "MinGPA": 3.0,
        "PreviousYearAcceptanceRates": null,
        "Term": "Fall, Spring, Summer",
        "LiveDate": null,
        "DeadlineDate": null,
        "Fees": 23400,
        "AverageScholarshipAmount": null,
        "CostPerCredit": 650,
        "ScholarshipAmount": null,
        "ScholarshipPercentage": null,
        "ScholarshipType": "Graduate Assistantships",
        "Program duration": "As little as two years",
        "Tuition fee": 23400,
        "Program name": "Master of Business Administration with Concentration in Strategic Marketing",
        "Program Page url": "https://www.uakron.edu/online/degrees/mba"
    },
    {
        "QsWorldRanking": null,
        "School": "College of Business",
        "MaxFails": null,
        "MaxGPA": 4.0,
        "MinGPA": 2.75,
        "PreviousYearAcceptanceRates": null,
        "Term": "Fall, Spring, Summer",
        "LiveDate": null,
        "DeadlineDate": null,
        "Fees": 29885.76,
        "AverageScholarshipAmount": null,
        "CostPerCredit": "$830.16 (Ohio Resident), $1,223.83 (Non-Ohio Resident)",
        "ScholarshipAmount": null,
        "ScholarshipPercentage": null,
        "ScholarshipType": "Graduate Assistantships, Endowed Scholarships",
        "Program duration": "As little as 12 months (full-time) or less than 2 years (part-time)",
        "Tuition fee": 29885.76,
        "Program name": "Master of Business Administration with Concentration in Supply Chain Management",
        "Program Page url": "https://www.uakron.edu/academics_majors/graduate_programs/"
    },
    {
        "QsWorldRanking": null,
        "School": "College of Business",
        "MaxFails": null,
        "MaxGPA": 4.0,
        "MinGPA": 3.0,
        "PreviousYearAcceptanceRates": null,
        "Term": "Fall, Spring, Summer",
        "LiveDate": null,
        "DeadlineDate": null,
        "Fees": null,
        "AverageScholarshipAmount": null,
        "CostPerCredit": "Ohio Resident: $717.75/credit; Non-Resident: $1036.63/credit. These 2023-24 rates include tuition ($541.02 Resident/$859.90 Non-Resident), a general fee ($64.15), and a graduate business program fee ($112.58).",
        "ScholarshipAmount": null,
        "ScholarshipPercentage": null,
        "ScholarshipType": "Graduate assistantships, Fellowships, Scholarships",
        "Program duration": null,
        "Tuition fee": null,
        "Program name": "Master of Science in Management with Concentration in Information Systems Management",
        "Program Page url": "https://bulletin.uakron.edu/graduate/colleges-programs/business-administration/management/information-systems-management-msm/"
    },
    {
        "QsWorldRanking": null,
        "School": "College of Business",
        "MaxFails": null,
        "MaxGPA": 4,
        "MinGPA": 3,
        "PreviousYearAcceptanceRates": null,
        "Term": "Fall, Spring, Summer",
        "LiveDate": null,
        "DeadlineDate": null,
        "Fees": "$859.45/credit (in-state), $1180.21/credit (out-of-state)",
        "AverageScholarshipAmount": null,
        "CostPerCredit": "$859.45/credit (in-state), $1180.21/credit (out-of-state)",
        "ScholarshipAmount": "$5,000 (Provost's Fellowship)",
        "ScholarshipPercentage": null,
        "ScholarshipType": "Assistantships, Fellowships, Scholarships",
        "Program duration": "As little as one year",
        "Tuition fee": "$859.45/credit (in-state), $1180.21/credit (out-of-state)",
        "Program name": "Master of Science in Management with Concentration in Technological Innovation",
        "Program Page url": "https://www.uakron.edu/academics_majors/graduate_programs/"
    },
    {
        "QsWorldRanking": null,
        "School": "College of Business",
        "MaxFails": null,
        "MaxGPA": 4.0,
        "MinGPA": 3.0,
        "PreviousYearAcceptanceRates": null,
        "Term": "Fall",
        "LiveDate": null,
        "DeadlineDate": null,
        "Fees": 20441.4,
        "AverageScholarshipAmount": null,
        "CostPerCredit": "Ohio Resident: $681.38, Non-Ohio Resident: $1,023.70",
        "ScholarshipAmount": null,
        "ScholarshipPercentage": null,
        "ScholarshipType": "Graduate assistantships, Merit-based scholarships",
        "Program duration": "1 year",
        "Tuition fee": 20441.4,
        "Program name": "Master of Science in Management with Concentration in Supply Chain Management",
        "Program Page url": "https://www.uakron.edu/academics_majors/graduate_programs/"
    },
    {
        "QsWorldRanking": null,
        "School": "Buchtel College of Arts and Sciences",
        "MaxFails": null,
        "MaxGPA": 4,
        "MinGPA": 3,
        "PreviousYearAcceptanceRates": null,
        "Term": "Fall",
        "LiveDate": null,
        "DeadlineDate": null,
        "Fees": "$56.55 per credit hour (General Service Fee)",
        "AverageScholarshipAmount": null,
        "CostPerCredit": "Ohio Resident: $594.31; Non-Ohio Resident: $881.01",
        "ScholarshipAmount": null,
        "ScholarshipPercentage": null,
        "ScholarshipType": "Graduate Assistantships",
        "Program duration": "2 years",
        "Tuition fee": "Approximately $10,698/year for Ohio residents and $15,858/year for non-residents, based on a typical load of 18 credits per year.",
        "Program name": "Master of Arts in Economics",
        "Program Page url": "https://www.uakron.edu/academics_majors/graduate_programs/"
    },
    {
        "QsWorldRanking": null,
        "School": "College of Business",
        "MaxFails": null,
        "MaxGPA": 4.0,
        "MinGPA": 3.0,
        "PreviousYearAcceptanceRates": null,
        "Term": "Fall, Spring, Summer",
        "LiveDate": null,
        "DeadlineDate": null,
        "Fees": "The tuition rate includes a College of Business Graduate Program Fee of $57.25 per credit hour and a General Service Fee (e.g., $60.25 per credit hour for 9+ credits).",
        "AverageScholarshipAmount": null,
        "CostPerCredit": "The total cost per credit hour for 2023-24 is approximately $800.88 for Ohio residents and $1,166.72 for non-residents, including all fees.",
        "ScholarshipAmount": null,
        "ScholarshipPercentage": null,
        "ScholarshipType": "Graduate assistantships, Merit-based scholarships",
        "Program duration": "30 semester credits. Can be completed in two or three semesters on a full-time basis.",
        "Tuition fee": "The estimated total program cost for 30 credits is $24,026.40 for Ohio residents and $35,001.60 for non-residents, based on 2023-24 tuition and fee rates.",
        "Program name": "Master of Taxation",
        "Program Page url": "https://www.uakron.edu/academics_majors/graduate_programs/"
    }
]